appmar/__init__.py
appmar/__main__.py
appmar/appmar-config.ini
appmar/appmar.py
appmar/ceman.png
appmar/libappmar.py
appmar/wave.png
appmar-1.0.1.dist-info/LICENSE
appmar-1.0.1.dist-info/METADATA
appmar-1.0.1.dist-info/WHEEL
appmar-1.0.1.dist-info/entry_points.txt
appmar-1.0.1.dist-info/top_level.txt
appmar-1.0.1.dist-info/RECORD
