Metadata-Version: 2.1
Name: appmar
Version: 1.0.1
Summary: Python program for marine climate analysis.
Home-page: https://github.com/cemanetwork/appmar
Author: CEMAN
Keywords: marine climate
Classifier: License :: OSI Approved :: MIT License
Requires-Python: >=3.7
License-File: LICENSE
Requires-Dist: cfgrib
Requires-Dist: gdal
Requires-Dist: wxpython
Requires-Dist: numpy
Requires-Dist: matplotlib (==3.2.*)
Requires-Dist: scipy
Requires-Dist: xarray
Requires-Dist: pandas
Requires-Dist: cartopy
Requires-Dist: scikit-learn
Requires-Dist: kneed
